simple_ses_mailer/__init__.py
simple_ses_mailer/mailers.py
simple_ses_mailer/utils.py
simple_ses_mailer-0.0.4.dist-info/LICENSE
simple_ses_mailer-0.0.4.dist-info/METADATA
simple_ses_mailer-0.0.4.dist-info/WHEEL
simple_ses_mailer-0.0.4.dist-info/top_level.txt
simple_ses_mailer-0.0.4.dist-info/RECORD
