Metadata-Version: 2.1
Name: simple-ses-mailer
Version: 0.0.4
Home-page: https://github.com/rez0n/simple-ses-mailer
Author: Denis Verbin <den.verbin@gmail.com>
License: Apache licence, see LICENCE
Keywords: aws,ses,mail
Classifier: Topic :: Communications :: Email
Requires: boto3
License-File: LICENSE
